date_guesser/__init__.py
date_guesser/constants.py
date_guesser/dates.py
date_guesser/guess_date.py
date_guesser/html.py
date_guesser/urls.py
date_guesser-2.1.4.dist-info/LICENSE
date_guesser-2.1.4.dist-info/METADATA
date_guesser-2.1.4.dist-info/WHEEL
date_guesser-2.1.4.dist-info/top_level.txt
date_guesser-2.1.4.dist-info/RECORD
