Metadata-Version: 1.1
Name: date-guesser
Version: 2.1.4
Summary: Extract publication dates from web pages
Home-page: https://github.com/mitmedialab/date_guesser
Author: Colin Carroll
Author-email: ccarroll@mit.edu
License: MIT
Platform: UNKNOWN
Classifier: Development Status :: 3 - Alpha
Classifier: Intended Audience :: Developers
Classifier: License :: OSI Approved :: MIT License
Classifier: Programming Language :: Python :: 3
Classifier: Programming Language :: Python :: 3.6
